perceval/__init__.py
perceval/algorithm/__init__.py
perceval/algorithm/abstract_algorithm.py
perceval/algorithm/analyzer.py
perceval/algorithm/sampler.py
perceval/algorithm/tomography/__init__.py
perceval/algorithm/tomography/abstract_process_tomography.py
perceval/algorithm/tomography/tomography.py
perceval/algorithm/tomography/tomography_mle.py
perceval/algorithm/tomography/tomography_utils.py
perceval/backends/__init__.py
perceval/backends/_abstract_backends.py
perceval/backends/_clifford2017.py
perceval/backends/_mps.py
perceval/backends/_naive.py
perceval/backends/_naive_approx.py
perceval/backends/_slap.py
perceval/backends/_slos.py
perceval/components/__init__.py
perceval/components/_decompose_perms.py
perceval/components/_mode_connector.py
perceval/components/_pauli.py
perceval/components/abstract_component.py
perceval/components/abstract_processor.py
perceval/components/component_catalog.py
perceval/components/detector.py
perceval/components/experiment.py
perceval/components/feed_forward_configurator.py
perceval/components/generic_interferometer.py
perceval/components/linear_circuit.py
perceval/components/non_unitary_components.py
perceval/components/port.py
perceval/components/processor.py
perceval/components/source.py
perceval/components/tomography_exp_configurer.py
perceval/components/unitary_components.py
perceval/components/core_catalog/__init__.py
perceval/components/core_catalog/controlled_rotation_gates.py
perceval/components/core_catalog/gates_1qubit.py
perceval/components/core_catalog/generic_2mode.py
perceval/components/core_catalog/heralded_cnot.py
perceval/components/core_catalog/heralded_cz.py
perceval/components/core_catalog/klm_cnot.py
perceval/components/core_catalog/mzi.py
perceval/components/core_catalog/postprocessed_ccz.py
perceval/components/core_catalog/postprocessed_cnot.py
perceval/components/core_catalog/postprocessed_cz.py
perceval/components/core_catalog/qloq_ansatz.py
perceval/components/core_catalog/toffoli.py
perceval_quandela-1.0.1.dist-info/licenses/LICENSE
perceval_quandela-1.0.1.dist-info/METADATA
perceval_quandela-1.0.1.dist-info/WHEEL
perceval_quandela-1.0.1.dist-info/top_level.txt
perceval_quandela-1.0.1.dist-info/RECORD
