Metadata-Version: 2.4
Name: perceval-quandela
Version: 1.0.1
Summary: A powerful Quantum Photonic Framework
Home-page: https://github.com/Quandela/Perceval
Author: quandela
Author-email: perceval@quandela.com
Project-URL: Documentation, https://perceval.quandela.net/docs/
Project-URL: Source, https://github.com/Quandela/Perceval
Project-URL: Tracker, https://github.com/Quandela/Perceval/issues
Classifier: Programming Language :: Python :: 3.9
Classifier: Programming Language :: Python :: 3.10
Classifier: Programming Language :: Python :: 3.11
Classifier: Programming Language :: Python :: 3.12
Classifier: Programming Language :: Python :: 3.13
Classifier: License :: OSI Approved :: MIT License
Classifier: Operating System :: OS Independent
Requires-Python: >=3.9,<3.14
License-File: LICENSE
Requires-Dist: sympy~=1.12
Requires-Dist: numpy<3,>=1.26
Requires-Dist: scipy~=1.13
Requires-Dist: tabulate~=0.9
Requires-Dist: matplotlib<4
Requires-Dist: exqalibur~=1.0.0
Requires-Dist: multipledispatch<2
Requires-Dist: protobuf>=3.20.3
Requires-Dist: drawsvg>=2.0
Requires-Dist: requests<3
Requires-Dist: networkx<4,>=3.1
Requires-Dist: latexcodec<4
Requires-Dist: platformdirs<5
Requires-Dist: tqdm
Requires-Dist: typing_extensions; python_version == "3.9"
Dynamic: author
Dynamic: author-email
Dynamic: classifier
Dynamic: description
Dynamic: description-content-type
Dynamic: home-page
Dynamic: license-file
Dynamic: project-url
Dynamic: requires-dist
Dynamic: requires-python
Dynamic: summary
